Metadata-Version: 2.1
Name: labelme-ytu
Version: 5.5.3
Summary: Image Polygonal Annotation with Python
Home-page: https://github.com/wkentaro/labelme
Author: Kentaro Wada
Author-email: www.kentaro.wada@gmail.com
License: GPLv3
Keywords: Image Annotation,Machine Learning
Classifier: Development Status :: 5 - Production/Stable
Classifier: Intended Audience :: Developers
Classifier: Intended Audience :: Science/Research
Classifier: Natural Language :: English
Classifier: Operating System :: OS Independent
Classifier: Programming Language :: Python
Classifier: Programming Language :: Python :: 3.5
Classifier: Programming Language :: Python :: 3.6
Classifier: Programming Language :: Python :: 3.7
Classifier: Programming Language :: Python :: 3.8
Classifier: Programming Language :: Python :: 3.9
Classifier: Programming Language :: Python :: 3 :: Only
License-File: LICENSE
